README.txt
setup.py
src/django_robust_i18n_urls.egg-info/PKG-INFO
src/django_robust_i18n_urls.egg-info/SOURCES.txt
src/django_robust_i18n_urls.egg-info/dependency_links.txt
src/django_robust_i18n_urls.egg-info/requires.txt
src/django_robust_i18n_urls.egg-info/top_level.txt
src/robust_urls/__init__.py
src/robust_urls/middleware.py
src/robust_urls/urls.py
src/robust_urls/utils.py
src/robust_urls/views.py