Metadata-Version: 1.0
Name: django-robust-i18n-urls
Version: 1.0.0
Summary: Robust internationalized urls implementation for Django.
Home-page: http://karolmajta.com/django-robust-i18n-urls/
Author: Karol Majta
Author-email: karolmajta@gmail.com
License: MIT
Platform: UNKNOWN
